LICENSE
MANIFEST.in
README.rst
setup.py
django_suit.egg-info/PKG-INFO
django_suit.egg-info/SOURCES.txt
django_suit.egg-info/dependency_links.txt
django_suit.egg-info/not-zip-safe
django_suit.egg-info/top_level.txt
docs/Makefile
docs/conf.py
docs/configuration.rst
docs/contributing.rst
docs/form_includes.rst
docs/form_tabs.rst
docs/index.rst
docs/js_css.rst
docs/list_attributes.rst
docs/sortables.rst
docs/widgets.rst
docs/wysiwyg.rst
docs/_static/img/changelist_sortable.png
docs/_static/img/ckeditor.png
docs/_static/img/collapse.png
docs/_static/img/dates.png
docs/_static/img/django-suit.png
docs/_static/img/enclosed_input.png
docs/_static/img/form_includes.png
docs/_static/img/form_tabs.png
docs/_static/img/full-width.png
docs/_static/img/linked_select.png
docs/_static/img/list_attributes.png
docs/_static/img/mptt_sortable.png
docs/_static/img/stacked_inline_sortable.png
docs/_static/img/tabular_inline_sortable.png
suit/__init__.py
suit/admin.py
suit/compat.py
suit/config.py
suit/models.py
suit/utils.py
suit/watch_less.py
suit/widgets.py
suit/static/admin/css/forms.css
suit/static/cms/css/pages.css
suit/static/suit/bootstrap/css/bootstrap.css
suit/static/suit/bootstrap/css/bootstrap.min.css
suit/static/suit/bootstrap/img/glyphicons-halflings-white-shadow.png
suit/static/suit/bootstrap/img/glyphicons-halflings-white.png
suit/static/suit/bootstrap/img/glyphicons-halflings.png
suit/static/suit/bootstrap/js/bootstrap.js
suit/static/suit/bootstrap/js/bootstrap.min.js
suit/static/suit/css/djangocms.css
suit/static/suit/css/filer.css
suit/static/suit/css/suit.css
suit/static/suit/img/ajax-loader.gif
suit/static/suit/img/bg_left_white.gif
suit/static/suit/img/bg_pattern.jpg
suit/static/suit/img/cc_active_nav.png
suit/static/suit/img/drag-handle.png
suit/static/suit/img/glyphicons-halflings-white-nav.png
suit/static/suit/img/glyphicons-halflings-white-shadow.png
suit/static/suit/js/djangocms.js
suit/static/suit/js/jquery-1.8.3.min.js
suit/static/suit/js/jquery.autosize-min.js
suit/static/suit/js/sortables.js
suit/static/suit/js/suit-form-confirm.js
suit/static/suit/js/suit.js
suit/static/suit/less/djangocms.less
suit/static/suit/less/filer.less
